qtasync/__init__.py
qtasync/_env.py
qtasync/_util.py
qtasync/qasyncio/__init__.py
qtasync/qasyncio/_env.py
qtasync/qasyncio/_loop.py
qtasync/qasyncio/_unix.py
qtasync/qasyncio/_util.py
qtasync/qasyncio/_windows.py
qtasync/qconcurrent/__init__.py
qtasync/qconcurrent/_futures.py
qtasync/qthreading/__init__.py
qtasync/qthreading/_locks.py
qtasync/qthreading/_thread.py
qtasync/qthreading/_timer.py
qtasync/types/__init__.py
qtasync/types/bound.py
qtasync/types/unbound.py
qtasync-0.3.1.dist-info/LICENSE
qtasync-0.3.1.dist-info/WHEEL
qtasync-0.3.1.dist-info/METADATA
qtasync-0.3.1.dist-info/RECORD
